Metadata-Version: 2.0
Name: odoo10-addon-account-banking-mandate-sale
Version: 10.0.1.0.1
Summary: Adds mandates on sale orders
Home-page: https://github.com/OCA/bank-payment
Author: Akretion, Odoo Community Association (OCA)
Author-email: support@odoo-community.org
License: AGPL-3
Platform: UNKNOWN
Classifier: Programming Language :: Python
Classifier: Framework :: Odoo
Classifier: License :: OSI Approved :: GNU Affero General Public License v3
Requires-Python: ~=2.7
Requires-Dist: odoo (<10.1dev,>=10.0)
Requires-Dist: odoo10-addon-account-banking-mandate
Requires-Dist: odoo10-addon-account-payment-sale
